__init__.py
cross_moment.py
cross_moment-0.0.1.dist-info/LICENSE
cross_moment-0.0.1.dist-info/METADATA
cross_moment-0.0.1.dist-info/WHEEL
cross_moment-0.0.1.dist-info/top_level.txt
cross_moment-0.0.1.dist-info/RECORD
