Metadata-Version: 2.1
Name: cross-moment
Version: 0.0.1
Summary: Package for cross-moment algorithm
Author-email: Yaroslav Kivva <26yaroslav@gmail.com>
Project-URL: Homepage, https://github.com/pypa/cross_moments
Project-URL: Bug Tracker, https://github.com/pypa/cross_moments/issues
Classifier: Programming Language :: Python :: 3
Classifier: License :: OSI Approved :: MIT License
Classifier: Operating System :: OS Independent
Requires-Python: >=3.7
License-File: LICENSE
